README.md
setup.py
isp_sdk/__init__.py
isp_sdk/errors.py
isp_sdk/methods.py
isp_sdk/sessions.py
isp_sdk.egg-info/PKG-INFO
isp_sdk.egg-info/SOURCES.txt
isp_sdk.egg-info/dependency_links.txt
isp_sdk.egg-info/requires.txt
isp_sdk.egg-info/top_level.txt