Metadata-Version: 1.0
Name: isp-sdk
Version: 0.4.3
Summary: ISP Panel Api SDK
Home-page: https://github.com/Underlor/isp_api
Author: Popov Aleksander
Author-email: admin@alexue4.ru
License: Creative Commons Attribution-Noncommercial-Share Alike license
Platform: UNKNOWN
